lzhsta/__init__.py
lzhsta/fit.py
lzhsta/para.py
lzhsta-1.0.0.dist-info/METADATA
lzhsta-1.0.0.dist-info/WHEEL
lzhsta-1.0.0.dist-info/top_level.txt
lzhsta-1.0.0.dist-info/RECORD
