Metadata-Version: 2.1
Name: lzhsta
Version: 1.0.0
Summary: A package for statistical analysis
Author-email: zhlei <leizuoho@mail.ustc.edu.cn>
Requires-Python: >=3.0
Requires-Dist: numpy
Requires-Dist: pandas
Requires-Dist: lmfit
Requires-Dist: scipy
